README.md
setup.py
IPCrawl/IPCrawl.py
IPCrawl/__init__.py
IPCrawl.egg-info/PKG-INFO
IPCrawl.egg-info/SOURCES.txt
IPCrawl.egg-info/dependency_links.txt
IPCrawl.egg-info/top_level.txt