Metadata-Version: 2.1
Name: IPCrawl
Version: 0.3
Summary: IPCrawl
Home-page: https://github.com/kabaBZ
Author: kabaBZ
Author-email: 1137088773@qq.com
Maintainer: 
Maintainer-email: 
License: MIT License
Platform: UNKNOWN
Classifier: Development Status :: 3 - Alpha
Classifier: Intended Audience :: Developers
Classifier: Topic :: Software Development :: Build Tools
Classifier: License :: OSI Approved :: MIT License
Classifier: Programming Language :: Python :: 3
Requires-Python: >=3.7
